webpty/__init__.py
webpty/index.html
webpty/server.py
webpty/static/webpty.css
webpty/static/webpty.js
webpty/static/webpty.min.css
webpty/static/webpty.min.js
webpty-3.9.dist-info/LICENSE
webpty-3.9.dist-info/METADATA
webpty-3.9.dist-info/WHEEL
webpty-3.9.dist-info/entry_points.txt
webpty-3.9.dist-info/RECORD
