Metadata-Version: 2.1
Name: webpty
Version: 3.9
Summary: A web-based application to access shell & shell based applications via a browser
License: OSI Approved :: MIT License
Author: Satheesh Kumar
Author-email: mail@satheesh.dev
Requires-Python: >=3.7,<=3.10
Classifier: License :: Other/Proprietary License
Classifier: Programming Language :: Python :: 3
Classifier: Programming Language :: Python :: 3.7
Classifier: Programming Language :: Python :: 3.8
Classifier: Programming Language :: Python :: 3.9
Classifier: Programming Language :: Python :: 3.10
Requires-Dist: importlib-metadata (>=5.1.0,<6.0.0)
Requires-Dist: requests (==2.28.1)
Requires-Dist: tornado (==6.2)
